superbus/__init__.py
superbus/client.py
superbus/updater.py
superbus/utils.py
superbus/worker.py
superbus-1.0.1.dist-info/METADATA
superbus-1.0.1.dist-info/WHEEL
superbus-1.0.1.dist-info/licenses/LICENSE
superbus-1.0.1.dist-info/RECORD
