Metadata-Version: 2.4
Name: superbus
Version: 1.0.1
Summary: Redis-based bus to communicate between microservices that handle long-running tasks
License: MIT
License-File: LICENSE
Keywords: redis,microservices,bus,async,tasks
Author: starrabb1t
Author-email: berzin@phystech.edu
Requires-Python: >=3.7
Classifier: License :: OSI Approved :: MIT License
Classifier: Programming Language :: Python :: 3
Classifier: Programming Language :: Python :: 3.7
Classifier: Programming Language :: Python :: 3.8
Classifier: Programming Language :: Python :: 3.9
Classifier: Programming Language :: Python :: 3.10
Classifier: Programming Language :: Python :: 3.11
Classifier: Programming Language :: Python :: 3.12
Classifier: Programming Language :: Python :: 3.13
Classifier: Programming Language :: Python :: 3.14
Requires-Dist: httpx (>=0.24.1)
Requires-Dist: pydantic (>=1.9.1,<3.0.0)
Requires-Dist: redis (>=3.5.3)
Project-URL: Homepage, https://github.com/starrabb1t/superbus
Project-URL: Repository, https://github.com/starrabb1t/superbus
